[{"line":1,"elements":[{"start_timestamp":"2022-08-02T10:13:32.327Z","line":12,"name":"google search feature","description":"","id":"google-search-feature;google-search-feature;;2","type":"scenario","keyword":"Scenario Outline","steps":[{"result":{"duration":8513838100,"status":"passed"},"line":4,"name":"browser is open","match":{"location":"StepDefinitions.googlesearchsteps.browser_is_open()"},"keyword":"Given "},{"result":{"duration":628814600,"status":"passed"},"line":5,"name":"user is on saucelabs pag","match":{"location":"StepDefinitions.googlesearchsteps.user_is_on_saucelabs_pag()"},"keyword":"And "},{"result":{"duration":577290800,"status":"passed"},"line":6,"name":"text in login creds with \"standard_user\" and \"secret_sauce\"","match":{"arguments":[{"val":"\"standard_user\"","offset":25},{"val":"\"secret_sauce\"","offset":45}],"location":"StepDefinitions.googlesearchsteps.text_in_login_creds_with_and(java.lang.String,java.lang.String)"},"keyword":"When "},{"result":{"duration":513380100,"status":"passed"},"line":7,"name":"hits submit","match":{"location":"StepDefinitions.googlesearchsteps.hits_submit()"},"keyword":"And "},{"result":{"duration":1778195900,"status":"passed"},"line":8,"name":"user is navigated with logincreds","match":{"location":"StepDefinitions.googlesearchsteps.user_is_navigated_with_logincreds()"},"keyword":"Then "}]},{"start_timestamp":"2022-08-02T10:13:44.723Z","line":13,"name":"google search feature","description":"","id":"google-search-feature;google-search-feature;;3","type":"scenario","keyword":"Scenario Outline","steps":[{"result":{"duration":2053136400,"status":"passed"},"line":4,"name":"browser is open","match":{"location":"StepDefinitions.googlesearchsteps.browser_is_open()"},"keyword":"Given "},{"result":{"duration":666855500,"status":"passed"},"line":5,"name":"user is on saucelabs pag","match":{"location":"StepDefinitions.googlesearchsteps.user_is_on_saucelabs_pag()"},"keyword":"And "},{"result":{"duration":529697700,"status":"passed"},"line":6,"name":"text in login creds with \"locked_out_user\" and \"secret_sauce\"","match":{"arguments":[{"val":"\"locked_out_user\"","offset":25},{"val":"\"secret_sauce\"","offset":47}],"location":"StepDefinitions.googlesearchsteps.text_in_login_creds_with_and(java.lang.String,java.lang.String)"},"keyword":"When "},{"result":{"duration":547685900,"status":"passed"},"line":7,"name":"hits submit","match":{"location":"StepDefinitions.googlesearchsteps.hits_submit()"},"keyword":"And "},{"result":{"duration":1911927900,"status":"passed"},"line":8,"name":"user is navigated with logincreds","match":{"location":"StepDefinitions.googlesearchsteps.user_is_navigated_with_logincreds()"},"keyword":"Then "}]},{"start_timestamp":"2022-08-02T10:13:50.470Z","line":14,"name":"google search feature","description":"","id":"google-search-feature;google-search-feature;;4","type":"scenario","keyword":"Scenario Outline","steps":[{"result":{"duration":2405933100,"status":"passed"},"line":4,"name":"browser is open","match":{"location":"StepDefinitions.googlesearchsteps.browser_is_open()"},"keyword":"Given "},{"result":{"duration":643133200,"status":"passed"},"line":5,"name":"user is on saucelabs pag","match":{"location":"StepDefinitions.googlesearchsteps.user_is_on_saucelabs_pag()"},"keyword":"And "},{"result":{"duration":452391400,"status":"passed"},"line":6,"name":"text in login creds with \"problem_user\" and \"secret_sauce\"","match":{"arguments":[{"val":"\"problem_user\"","offset":25},{"val":"\"secret_sauce\"","offset":44}],"location":"StepDefinitions.googlesearchsteps.text_in_login_creds_with_and(java.lang.String,java.lang.String)"},"keyword":"When "},{"result":{"duration":158908700,"status":"passed"},"line":7,"name":"hits submit","match":{"location":"StepDefinitions.googlesearchsteps.hits_submit()"},"keyword":"And "},{"result":{"duration":2559238400,"status":"passed"},"line":8,"name":"user is navigated with logincreds","match":{"location":"StepDefinitions.googlesearchsteps.user_is_navigated_with_logincreds()"},"keyword":"Then "}]},{"start_timestamp":"2022-08-02T10:13:56.714Z","line":15,"name":"google search feature","description":"","id":"google-search-feature;google-search-feature;;5","type":"scenario","keyword":"Scenario Outline","steps":[{"result":{"duration":2373029300,"status":"passed"},"line":4,"name":"browser is open","match":{"location":"StepDefinitions.googlesearchsteps.browser_is_open()"},"keyword":"Given "},{"result":{"duration":1117765700,"status":"passed"},"line":5,"name":"user is on saucelabs pag","match":{"location":"StepDefinitions.googlesearchsteps.user_is_on_saucelabs_pag()"},"keyword":"And "},{"result":{"duration":526699100,"status":"passed"},"line":6,"name":"text in login creds with \"performance_glitch_user\" and \"secret_sauce\"","match":{"arguments":[{"val":"\"performance_glitch_user\"","offset":25},{"val":"\"secret_sauce\"","offset":55}],"location":"StepDefinitions.googlesearchsteps.text_in_login_creds_with_and(java.lang.String,java.lang.String)"},"keyword":"When "},{"result":{"duration":437750000,"status":"passed"},"line":7,"name":"hits submit","match":{"location":"StepDefinitions.googlesearchsteps.hits_submit()"},"keyword":"And "},{"result":{"duration":2019931700,"status":"passed"},"line":8,"name":"user is navigated with logincreds","match":{"location":"StepDefinitions.googlesearchsteps.user_is_navigated_with_logincreds()"},"keyword":"Then "}]}],"name":"google search feature","description":"","id":"google-search-feature","keyword":"Feature","uri":"file:src/test/resources/features/loginpage.feature","tags":[]},{"line":1,"elements":[{"start_timestamp":"2022-08-02T10:14:03.223Z","line":12,"name":"google search feature","description":"","id":"google-search-feature;google-search-feature;;2","type":"scenario","keyword":"Scenario Outline","steps":[{"result":{"duration":2667966600,"status":"passed"},"line":4,"name":"browser is open","match":{"location":"StepDefinitions.googlesearchsteps.browser_is_open()"},"keyword":"Given "},{"result":{"duration":666354300,"status":"passed"},"line":5,"name":"user is on saucelabs pag","match":{"location":"StepDefinitions.googlesearchsteps.user_is_on_saucelabs_pag()"},"keyword":"And "},{"result":{"duration":479725700,"status":"passed"},"line":6,"name":"text in login creds with \"standard_user\" and \"secret_sauce\"","match":{"arguments":[{"val":"\"standard_user\"","offset":25},{"val":"\"secret_sauce\"","offset":45}],"location":"StepDefinitions.googlesearchsteps.text_in_login_creds_with_and(java.lang.String,java.lang.String)"},"keyword":"When "},{"result":{"duration":272843400,"status":"passed"},"line":7,"name":"hits submit","match":{"location":"StepDefinitions.googlesearchsteps.hits_submit()"},"keyword":"And "},{"result":{"duration":2619516800,"status":"passed"},"line":8,"name":"user is navigated with logincreds","match":{"location":"StepDefinitions.googlesearchsteps.user_is_navigated_with_logincreds()"},"keyword":"Then "}]}],"name":"google search feature","description":"","id":"google-search-feature","keyword":"Feature","uri":"file:src/test/resources/features/loginpage2.feature","tags":[]},{"line":1,"elements":[{"start_timestamp":"2022-08-02T10:14:09.969Z","line":12,"name":"google search feature","description":"","id":"google-search-feature;google-search-feature;;2","type":"scenario","keyword":"Scenario Outline","steps":[{"result":{"duration":2081093400,"status":"passed"},"line":4,"name":"browser is open","match":{"location":"StepDefinitions.googlesearchsteps.browser_is_open()"},"keyword":"Given "},{"result":{"duration":1902107700,"status":"passed"},"line":5,"name":"user is on saucelabs pag","match":{"location":"StepDefinitions.googlesearchsteps.user_is_on_saucelabs_pag()"},"keyword":"And "},{"result":{"duration":487720700,"status":"passed"},"line":6,"name":"text in login creds with \"standard_user\" and \"secret_sauce\"","match":{"arguments":[{"val":"\"standard_user\"","offset":25},{"val":"\"secret_sauce\"","offset":45}],"location":"StepDefinitions.googlesearchsteps.text_in_login_creds_with_and(java.lang.String,java.lang.String)"},"keyword":"When "},{"result":{"duration":575670200,"status":"passed"},"line":7,"name":"hits submit","match":{"location":"StepDefinitions.googlesearchsteps.hits_submit()"},"keyword":"And "},{"result":{"duration":1769371200,"status":"passed"},"line":8,"name":"user is navigated with logincreds","match":{"location":"StepDefinitions.googlesearchsteps.user_is_navigated_with_logincreds()"},"keyword":"Then "}]},{"start_timestamp":"2022-08-02T10:14:16.817Z","line":13,"name":"google search feature","description":"","id":"google-search-feature;google-search-feature;;3","type":"scenario","keyword":"Scenario Outline","steps":[{"result":{"duration":2007832000,"status":"passed"},"line":4,"name":"browser is open","match":{"location":"StepDefinitions.googlesearchsteps.browser_is_open()"},"keyword":"Given "},{"result":{"duration":572672700,"status":"passed"},"line":5,"name":"user is on saucelabs pag","match":{"location":"StepDefinitions.googlesearchsteps.user_is_on_saucelabs_pag()"},"keyword":"And "},{"result":{"duration":327812800,"status":"passed"},"line":6,"name":"text in login creds with \"locked_out_user\" and \"secret_sauce\"","match":{"arguments":[{"val":"\"locked_out_user\"","offset":25},{"val":"\"secret_sauce\"","offset":47}],"location":"StepDefinitions.googlesearchsteps.text_in_login_creds_with_and(java.lang.String,java.lang.String)"},"keyword":"When "},{"result":{"duration":186963900,"status":"passed"},"line":7,"name":"hits submit","match":{"location":"StepDefinitions.googlesearchsteps.hits_submit()"},"keyword":"And "},{"result":{"duration":2467457000,"status":"passed"},"line":8,"name":"user is navigated with logincreds","match":{"location":"StepDefinitions.googlesearchsteps.user_is_navigated_with_logincreds()"},"keyword":"Then "}]}],"name":"google search feature","description":"","id":"google-search-feature","keyword":"Feature","uri":"file:src/test/resources/features/loginpage3.feature","tags":[]}]